README.md
gpu_lib.so
setup.py
phe_cuda/__about__.py
phe_cuda/__init__.py
phe_cuda/command_line.py
phe_cuda/encoding.py
phe_cuda/gpu_lib.so
phe_cuda/paillier.py
phe_cuda/util.py
phe_cuda.egg-info/PKG-INFO
phe_cuda.egg-info/SOURCES.txt
phe_cuda.egg-info/dependency_links.txt
phe_cuda.egg-info/top_level.txt
tests/__init__.py
tests/cli_test.py
tests/math_test.py
tests/paillier_test.py
tests/util_test.py